Impeller/__init__.py
Impeller/baseline.py
Impeller/config.py
Impeller/data.py
Impeller/main.py
Impeller/model.py
Impeller/train.py
Impeller/utils.py
impeller-0.1.2.dist-info/METADATA
impeller-0.1.2.dist-info/WHEEL
impeller-0.1.2.dist-info/entry_points.txt
impeller-0.1.2.dist-info/top_level.txt
impeller-0.1.2.dist-info/RECORD
