Metadata-Version: 2.1
Name: impeller
Version: 0.1.2
Summary: Impeller is a package for spatial transcriptomics imputation using path-based graph neural networks.
Home-page: https://github.com/aicb-ZhangLabs/Impeller
Author: Ziheng Duan
Author-email: duanziheng1206@gmail.com
Classifier: Programming Language :: Python :: 3
Classifier: License :: OSI Approved :: MIT License
Classifier: Operating System :: OS Independent
Requires-Python: >=3.6
Requires-Dist: torch
Requires-Dist: gdown
Requires-Dist: scanpy
Requires-Dist: pandas
Requires-Dist: numpy
Requires-Dist: scikit-learn
Requires-Dist: dgl
